lumo_core/__init__.py
lumo_core/core/__init__.py
lumo_core/core/attr.py
lumo_core/core/disk.py
lumo_core/core/enums.py
lumo_core/core/interp.py
lumo_core/core/list.py
lumo_core/core/metaclasses.py
lumo_core/core/meter.py
lumo_core/core/params.py
lumo_core/core/raises.py
lumo_core/core/record.py
lumo_core/core/table.py
lumo_core/core/tree.py
lumo_core/core/record_backend/__init__.py
lumo_core/core/record_backend/abc.py
lumo_core/core/record_backend/record_csv.py
lumo_core/core/record_backend/record_sqlite.py
lumo_core/core/record_backend/record_tb.py
lumo_core/core/record_backend/record_wandb.py
lumo_core/decorators/__init__.py
lumo_core/decorators/clsmethod.py
lumo_core/decorators/deprecated.py
lumo_core/decorators/lazy_required.py
lumo_core/decorators/map_extract.py
lumo_core/decorators/process.py
lumo_core/decorators/regist.py
lumo_core/proc/__init__.py
lumo_core/proc/config.py
lumo_core/proc/date.py
lumo_core/proc/dependency.py
lumo_core/proc/dist.py
lumo_core/proc/network.py
lumo_core/proc/path.py
lumo_core/utils/__init__.py
lumo_core/utils/ast.py
lumo_core/utils/exithook.py
lumo_core/utils/filelock.py
lumo_core/utils/filelock2.py
lumo_core/utils/fmt.py
lumo_core/utils/hash.py
lumo_core/utils/logger.py
lumo_core/utils/random.py
lumo_core/utils/repository.py
lumo_core/utils/safe_io.py
lumo_core/utils/screen.py
lumo_core/utils/timer.py
lumo_core-0.1.1.dist-info/LICENSE
lumo_core-0.1.1.dist-info/METADATA
lumo_core-0.1.1.dist-info/WHEEL
lumo_core-0.1.1.dist-info/top_level.txt
lumo_core-0.1.1.dist-info/RECORD
